stopro/__init__.py
stopro/_utils.py
stopro/colored_geometric_brownian_motion.py
stopro/colored_replicator.py
stopro/competitive_lotka_volterra.py
stopro/exponential_ornstein_uhlenbeck.py
stopro/geometric_brownian_motion.py
stopro/gillespie_replicator.py
stopro/integrated_ornstein_uhlenbeck.py
stopro/kimura_replicator.py
stopro/moran.py
stopro/ornstein_uhlenbeck.py
stopro/white_replicator.py
stopro/wiener.py
stopro-0.7.0.dist-info/WHEEL
stopro-0.7.0.dist-info/METADATA
stopro-0.7.0.dist-info/RECORD
