Metadata-Version: 2.3
Name: stopro
Version: 0.7.0
Summary: Stochastic processes in Python
Keywords: stochastic-processes,sde,wiener,ornstein-uhlenbeck
Author: Dirk Brockmann
Author-email: Dirk Brockmann <dirk.brockmann@tu-dresden.de>
License: MIT
Classifier: Programming Language :: Python :: 3
Classifier: License :: OSI Approved :: MIT License
Classifier: Operating System :: OS Independent
Requires-Dist: numpy>=1.22,<3
Requires-Dist: scipy>=1.9,<2
Requires-Dist: tqdm>=4.66 ; extra == 'bench'
Requires-Dist: jupyterlab ; extra == 'examples'
Requires-Dist: matplotlib>=3.7 ; extra == 'examples'
Requires-Dist: palettable ; extra == 'examples'
Maintainer: Dirk Brockmann
Maintainer-email: Dirk Brockmann <dirk.brockmann@tu-dresden.de>
Requires-Python: >=3.10, <=3.13
Project-URL: Repository, https://github.com/dirkbrockmann/stopro
Provides-Extra: bench
Provides-Extra: examples
